pipco/__init__.py
pipco/__version__.py
pipco/main.py
pipco-0.0.19.dist-info/LICENSE
pipco-0.0.19.dist-info/METADATA
pipco-0.0.19.dist-info/WHEEL
pipco-0.0.19.dist-info/entry_points.txt
pipco-0.0.19.dist-info/top_level.txt
pipco-0.0.19.dist-info/RECORD
